{"m_DefineSymbols":{"m_Value":{"Android":"FUSION_WEAVER;FUSION2;FUSION_LOGLEVEL_DEBUG;USE_INPUT_SYSTEM_POSE_CONTROL;USE_STICK_CONTROL_THUMBSTICKS;APP_UI_EDITOR_ONLY;OVR_DISABLE_HAND_PINCH_BUTTON_MAPPING;FUSION_2;FUSION_2_0;FUSION_2_0_12;FUSION_2_OR_NEWER;FUSION_2_0_OR_NEWER","EmbeddedLinux":"FUSION_LOGLEVEL_DEBUG","GameCoreScarlett":"FUSION_LOGLEVEL_DEBUG","GameCoreXboxOne":"FUSION_LOGLEVEL_DEBUG","Kepler":"FUSION_LOGLEVEL_DEBUG","LinuxHeadlessSimulation":"FUSION_LOGLEVEL_DEBUG","Nintendo Switch":"FUSION_LOGLEVEL_DEBUG","Nintendo Switch 2":"FUSION_LOGLEVEL_DEBUG","PS4":"FUSION_LOGLEVEL_DEBUG","PS5":"FUSION_LOGLEVEL_DEBUG","QNX":"FUSION_LOGLEVEL_DEBUG","Server":"FUSION_WEAVER;FUSION2;FUSION_LOGLEVEL_DEBUG;FUSION_2;FUSION_2_0;FUSION_2_0_12;FUSION_2_OR_NEWER;FUSION_2_0_OR_NEWER","Standalone":"FUSION_WEAVER;FUSION2;FUSION_2;FUSION_2_0;FUSION_2_0_9;FUSION_2_OR_NEWER;FUSION_2_0_OR_NEWER;FUSION_LOGLEVEL_DEBUG;USE_INPUT_SYSTEM_POSE_CONTROL;USE_STICK_CONTROL_THUMBSTICKS;APP_UI_EDITOR_ONLY;OVR_DISABLE_HAND_PINCH_BUTTON_MAPPING","VisionOS":"FUSION_LOGLEVEL_DEBUG","WebGL":"FUSION_LOGLEVEL_DEBUG","Windows Store Apps":"FUSION_LOGLEVEL_DEBUG;USE_INPUT_SYSTEM_POSE_CONTROL;USE_STICK_CONTROL_THUMBSTICKS","XboxOne":"FUSION_LOGLEVEL_DEBUG","iPhone":"FUSION_LOGLEVEL_DEBUG","tvOS":"FUSION_LOGLEVEL_DEBUG"},"m_Initialized":true},"m_AllowUnsafeCode":{"m_Value":false,"m_Initialized":false},"m_ScriptDebugInfoEnabled":{"m_Value":true,"m_Initialized":true}}